pysyphe/__init__.py
pysyphe/actions.py
pysyphe/data_structs.py
pysyphe/exceptions.py
pysyphe/pipeline_test_suite.py
pysyphe/py2.py
pysyphe/py3.py
pysyphe/streamers.py
pysyphe/transactions.py
pysyphe-0.10.2.dist-info/AUTHORS
pysyphe-0.10.2.dist-info/LICENSE
pysyphe-0.10.2.dist-info/METADATA
pysyphe-0.10.2.dist-info/WHEEL
pysyphe-0.10.2.dist-info/pbr.json
pysyphe-0.10.2.dist-info/top_level.txt
pysyphe-0.10.2.dist-info/RECORD
