Metadata-Version: 2.1
Name: pysyphe
Version: 0.10.2
Summary: Helps you create and manage your own rollbackable transactions.
Home-page: https://github.com/SewanDevs/pysyphe
Author: Adrian Vandier Ast
Author-email: adrian.vandierast@sewan.fr
License: UNKNOWN
Platform: UNKNOWN
Classifier: Development Status :: 4 - Beta
Classifier: Intended Audience :: Information Technology
Classifier: Intended Audience :: Developers
Classifier: License :: OSI Approved :: Mozilla Public License 2.0 (MPL 2.0)
Classifier: Operating System :: OS Independent
Classifier: Programming Language :: Python
Classifier: Programming Language :: Python :: 2
Classifier: Programming Language :: Python :: 2.7
Classifier: Programming Language :: Python :: 3
Classifier: Programming Language :: Python :: 3.6
